afc.py
afc-24.10.20.dist-info/METADATA
afc-24.10.20.dist-info/WHEEL
afc-24.10.20.dist-info/top_level.txt
afc-24.10.20.dist-info/RECORD
