Metadata-Version: 2.1
Name: afc
Version: 24.10.20
Summary: Realiza a avaliação de trabalhos na Feira de Ciências do CAp-UERJ
Requires-Python: >=3.12
Requires-Dist: docopt >=0.6.2
Requires-Dist: openpyxl >=3.1.5
Requires-Dist: pandas >=2.2.3
